{"nodes": [{"id": "c_users_mw_downloads_coding_pz_lua_shared_logs_islogsystem_lua", "label": "ISLogSystem.lua", "file_type": "code", "source_file": "lua/shared/Logs/ISLogSystem.lua", "source_location": "L1"}, {"id": "logs_islogsystem_inbrackets", "label": "inBrackets()", "file_type": "code", "source_file": "lua/shared/Logs/ISLogSystem.lua", "source_location": "L11"}, {"id": "logs_islogsystem_findcharacter", "label": "findCharacter()", "file_type": "code", "source_file": "lua/shared/Logs/ISLogSystem.lua", "source_location": "L13"}, {"id": "logs_islogsystem_islogsystem_getgenericlogtext", "label": "ISLogSystem.getGenericLogText()", "file_type": "code", "source_file": "lua/shared/Logs/ISLogSystem.lua", "source_location": "L26"}, {"id": "logs_islogsystem_islogsystem_getobjectposition", "label": "ISLogSystem.getObjectPosition()", "file_type": "code", "source_file": "lua/shared/Logs/ISLogSystem.lua", "source_location": "L47"}, {"id": "logs_islogsystem_islogsystem_logaction", "label": "ISLogSystem.logAction()", "file_type": "code", "source_file": "lua/shared/Logs/ISLogSystem.lua", "source_location": "L65"}, {"id": "logs_islogsystem_islogsystem_writelog", "label": "ISLogSystem.writeLog()", "file_type": "code", "source_file": "lua/shared/Logs/ISLogSystem.lua", "source_location": "L108"}, {"id": "logs_islogsystem_islogsystem_sendlog", "label": "ISLogSystem.sendLog()", "file_type": "code", "source_file": "lua/shared/Logs/ISLogSystem.lua", "source_location": "L122"}, {"id": "logs_islogsystem_islogsystem_onclientcommand", "label": "ISLogSystem.OnClientCommand()", "file_type": "code", "source_file": "lua/shared/Logs/ISLogSystem.lua", "source_location": "L130"}, {"id": "logs_islogsystem_islogsystem_init", "label": "ISLogSystem.init()", "file_type": "code", "source_file": "lua/shared/Logs/ISLogSystem.lua", "source_location": "L143"}], "edges": [{"source": "c_users_mw_downloads_coding_pz_lua_shared_logs_islogsystem_lua", "target": "logs_islogsystem_inbrackets", "relation": "contains", "confidence": "EXTRACTED", "source_file": "lua/shared/Logs/ISLogSystem.lua", "source_location": "L11", "weight": 1.0}, {"source": "c_users_mw_downloads_coding_pz_lua_shared_logs_islogsystem_lua", "target": "logs_islogsystem_findcharacter", "relation": "contains", "confidence": "EXTRACTED", "source_file": "lua/shared/Logs/ISLogSystem.lua", "source_location": "L13", "weight": 1.0}, {"source": "c_users_mw_downloads_coding_pz_lua_shared_logs_islogsystem_lua", "target": "logs_islogsystem_islogsystem_getgenericlogtext", "relation": "contains", "confidence": "EXTRACTED", "source_file": "lua/shared/Logs/ISLogSystem.lua", "source_location": "L26", "weight": 1.0}, {"source": "c_users_mw_downloads_coding_pz_lua_shared_logs_islogsystem_lua", "target": "logs_islogsystem_islogsystem_getobjectposition", "relation": "contains", "confidence": "EXTRACTED", "source_file": "lua/shared/Logs/ISLogSystem.lua", "source_location": "L47", "weight": 1.0}, {"source": "c_users_mw_downloads_coding_pz_lua_shared_logs_islogsystem_lua", "target": "logs_islogsystem_islogsystem_logaction", "relation": "contains", "confidence": "EXTRACTED", "source_file": "lua/shared/Logs/ISLogSystem.lua", "source_location": "L65", "weight": 1.0}, {"source": "c_users_mw_downloads_coding_pz_lua_shared_logs_islogsystem_lua", "target": "logs_islogsystem_islogsystem_writelog", "relation": "contains", "confidence": "EXTRACTED", "source_file": "lua/shared/Logs/ISLogSystem.lua", "source_location": "L108", "weight": 1.0}, {"source": "c_users_mw_downloads_coding_pz_lua_shared_logs_islogsystem_lua", "target": "logs_islogsystem_islogsystem_sendlog", "relation": "contains", "confidence": "EXTRACTED", "source_file": "lua/shared/Logs/ISLogSystem.lua", "source_location": "L122", "weight": 1.0}, {"source": "c_users_mw_downloads_coding_pz_lua_shared_logs_islogsystem_lua", "target": "logs_islogsystem_islogsystem_onclientcommand", "relation": "contains", "confidence": "EXTRACTED", "source_file": "lua/shared/Logs/ISLogSystem.lua", "source_location": "L130", "weight": 1.0}, {"source": "c_users_mw_downloads_coding_pz_lua_shared_logs_islogsystem_lua", "target": "logs_islogsystem_islogsystem_init", "relation": "contains", "confidence": "EXTRACTED", "source_file": "lua/shared/Logs/ISLogSystem.lua", "source_location": "L143", "weight": 1.0}, {"source": "logs_islogsystem_islogsystem_getgenericlogtext", "target": "logs_islogsystem_inbrackets", "relation": "calls", "context": "call", "confidence": "EXTRACTED", "source_file": "lua/shared/Logs/ISLogSystem.lua", "source_location": "L30", "weight": 1.0}, {"source": "logs_islogsystem_islogsystem_getgenericlogtext", "target": "logs_islogsystem_islogsystem_getobjectposition", "relation": "calls", "context": "call", "confidence": "EXTRACTED", "source_file": "lua/shared/Logs/ISLogSystem.lua", "source_location": "L39", "weight": 1.0}, {"source": "logs_islogsystem_islogsystem_logaction", "target": "logs_islogsystem_findcharacter", "relation": "calls", "context": "call", "confidence": "EXTRACTED", "source_file": "lua/shared/Logs/ISLogSystem.lua", "source_location": "L73", "weight": 1.0}, {"source": "logs_islogsystem_islogsystem_logaction", "target": "logs_islogsystem_islogsystem_getobjectposition", "relation": "calls", "context": "call", "confidence": "EXTRACTED", "source_file": "lua/shared/Logs/ISLogSystem.lua", "source_location": "L80", "weight": 1.0}, {"source": "logs_islogsystem_islogsystem_logaction", "target": "logs_islogsystem_inbrackets", "relation": "calls", "context": "call", "confidence": "EXTRACTED", "source_file": "lua/shared/Logs/ISLogSystem.lua", "source_location": "L93", "weight": 1.0}, {"source": "logs_islogsystem_islogsystem_logaction", "target": "logs_islogsystem_islogsystem_sendlog", "relation": "calls", "context": "call", "confidence": "EXTRACTED", "source_file": "lua/shared/Logs/ISLogSystem.lua", "source_location": "L96", "weight": 1.0}], "raw_calls": [{"caller_nid": "logs_islogsystem_inbrackets", "callee": "tostring", "is_member_call": false, "source_file": "C:\\Users\\MW\\Downloads\\coding\\PZ\\lua\\shared\\Logs\\ISLogSystem.lua", "source_location": "L11", "receiver": null}, {"caller_nid": "logs_islogsystem_findcharacter", "callee": "instanceof", "is_member_call": false, "source_file": "C:\\Users\\MW\\Downloads\\coding\\PZ\\lua\\shared\\Logs\\ISLogSystem.lua", "source_location": "L15", "receiver": null}, {"caller_nid": "logs_islogsystem_findcharacter", "callee": "getSpecificPlayer", "is_member_call": false, "source_file": "C:\\Users\\MW\\Downloads\\coding\\PZ\\lua\\shared\\Logs\\ISLogSystem.lua", "source_location": "L16", "receiver": null}, {"caller_nid": "logs_islogsystem_findcharacter", "callee": "getSpecificPlayer", "is_member_call": false, "source_file": "C:\\Users\\MW\\Downloads\\coding\\PZ\\lua\\shared\\Logs\\ISLogSystem.lua", "source_location": "L17", "receiver": null}, {"caller_nid": "logs_islogsystem_islogsystem_getobjectposition", "callee": "instanceof", "is_member_call": false, "source_file": "C:\\Users\\MW\\Downloads\\coding\\PZ\\lua\\shared\\Logs\\ISLogSystem.lua", "source_location": "L48", "receiver": null}, {"caller_nid": "logs_islogsystem_islogsystem_getobjectposition", "callee": "math.floor", "is_member_call": false, "source_file": "C:\\Users\\MW\\Downloads\\coding\\PZ\\lua\\shared\\Logs\\ISLogSystem.lua", "source_location": "L49", "receiver": null}, {"caller_nid": "logs_islogsystem_islogsystem_getobjectposition", "callee": "math.floor", "is_member_call": false, "source_file": "C:\\Users\\MW\\Downloads\\coding\\PZ\\lua\\shared\\Logs\\ISLogSystem.lua", "source_location": "L49", "receiver": null}, {"caller_nid": "logs_islogsystem_islogsystem_getobjectposition", "callee": "math.floor", "is_member_call": false, "source_file": "C:\\Users\\MW\\Downloads\\coding\\PZ\\lua\\shared\\Logs\\ISLogSystem.lua", "source_location": "L49", "receiver": null}, {"caller_nid": "logs_islogsystem_islogsystem_logaction", "callee": "isClient", "is_member_call": false, "source_file": "C:\\Users\\MW\\Downloads\\coding\\PZ\\lua\\shared\\Logs\\ISLogSystem.lua", "source_location": "L66", "receiver": null}, {"caller_nid": "logs_islogsystem_islogsystem_logaction", "callee": "getServerOptions", "is_member_call": false, "source_file": "C:\\Users\\MW\\Downloads\\coding\\PZ\\lua\\shared\\Logs\\ISLogSystem.lua", "source_location": "L70", "receiver": null}, {"caller_nid": "logs_islogsystem_islogsystem_logaction", "callee": "string.match", "is_member_call": false, "source_file": "C:\\Users\\MW\\Downloads\\coding\\PZ\\lua\\shared\\Logs\\ISLogSystem.lua", "source_location": "L71", "receiver": null}, {"caller_nid": "logs_islogsystem_islogsystem_logaction", "callee": "table.insert", "is_member_call": false, "source_file": "C:\\Users\\MW\\Downloads\\coding\\PZ\\lua\\shared\\Logs\\ISLogSystem.lua", "source_location": "L77", "receiver": null}, {"caller_nid": "logs_islogsystem_islogsystem_logaction", "callee": "table.insert", "is_member_call": false, "source_file": "C:\\Users\\MW\\Downloads\\coding\\PZ\\lua\\shared\\Logs\\ISLogSystem.lua", "source_location": "L78", "receiver": null}, {"caller_nid": "logs_islogsystem_islogsystem_logaction", "callee": "table.insert", "is_member_call": false, "source_file": "C:\\Users\\MW\\Downloads\\coding\\PZ\\lua\\shared\\Logs\\ISLogSystem.lua", "source_location": "L79", "receiver": null}, {"caller_nid": "logs_islogsystem_islogsystem_logaction", "callee": "table.insert", "is_member_call": false, "source_file": "C:\\Users\\MW\\Downloads\\coding\\PZ\\lua\\shared\\Logs\\ISLogSystem.lua", "source_location": "L80", "receiver": null}, {"caller_nid": "logs_islogsystem_islogsystem_logaction", "callee": "ipairs", "is_member_call": false, "source_file": "C:\\Users\\MW\\Downloads\\coding\\PZ\\lua\\shared\\Logs\\ISLogSystem.lua", "source_location": "L85", "receiver": null}, {"caller_nid": "logs_islogsystem_islogsystem_logaction", "callee": "table.insert", "is_member_call": false, "source_file": "C:\\Users\\MW\\Downloads\\coding\\PZ\\lua\\shared\\Logs\\ISLogSystem.lua", "source_location": "L86", "receiver": null}, {"caller_nid": "logs_islogsystem_islogsystem_logaction", "callee": "ipairs", "is_member_call": false, "source_file": "C:\\Users\\MW\\Downloads\\coding\\PZ\\lua\\shared\\Logs\\ISLogSystem.lua", "source_location": "L92", "receiver": null}, {"caller_nid": "logs_islogsystem_islogsystem_writelog", "callee": "writeLog", "is_member_call": false, "source_file": "C:\\Users\\MW\\Downloads\\coding\\PZ\\lua\\shared\\Logs\\ISLogSystem.lua", "source_location": "L109", "receiver": null}, {"caller_nid": "logs_islogsystem_islogsystem_sendlog", "callee": "isClient", "is_member_call": false, "source_file": "C:\\Users\\MW\\Downloads\\coding\\PZ\\lua\\shared\\Logs\\ISLogSystem.lua", "source_location": "L123", "receiver": null}, {"caller_nid": "logs_islogsystem_islogsystem_sendlog", "callee": "sendClientCommand", "is_member_call": false, "source_file": "C:\\Users\\MW\\Downloads\\coding\\PZ\\lua\\shared\\Logs\\ISLogSystem.lua", "source_location": "L124", "receiver": null}, {"caller_nid": "logs_islogsystem_islogsystem_onclientcommand", "callee": "ISLogSystem[_command]", "is_member_call": false, "source_file": "C:\\Users\\MW\\Downloads\\coding\\PZ\\lua\\shared\\Logs\\ISLogSystem.lua", "source_location": "L135", "receiver": null}, {"caller_nid": "logs_islogsystem_islogsystem_init", "callee": "getCurrentUserSteamID", "is_member_call": false, "source_file": "C:\\Users\\MW\\Downloads\\coding\\PZ\\lua\\shared\\Logs\\ISLogSystem.lua", "source_location": "L144", "receiver": null}]}