{"nodes": [{"id": "c_users_mw_downloads_coding_pz_lua_client_tests_recipetests_lua", "label": "RecipeTests.lua", "file_type": "code", "source_file": "lua/client/Tests/RecipeTests.lua", "source_location": "L1"}, {"id": "tests_recipetests_createsourceitem1", "label": "CreateSourceItem1()", "file_type": "code", "source_file": "lua/client/Tests/RecipeTests.lua", "source_location": "L1"}, {"id": "tests_recipetests_addtoinv", "label": "addToInv()", "file_type": "code", "source_file": "lua/client/Tests/RecipeTests.lua", "source_location": "L30"}, {"id": "tests_recipetests_getnumberofitem", "label": "getNumberOfItem()", "file_type": "code", "source_file": "lua/client/Tests/RecipeTests.lua", "source_location": "L43"}, {"id": "tests_recipetests_createsourceitem2", "label": "CreateSourceItem2()", "file_type": "code", "source_file": "lua/client/Tests/RecipeTests.lua", "source_location": "L53"}, {"id": "tests_recipetests_createsourceitem", "label": "CreateSourceItem()", "file_type": "code", "source_file": "lua/client/Tests/RecipeTests.lua", "source_location": "L80"}, {"id": "tests_recipetests_setupcontainers", "label": "SetupContainers()", "file_type": "code", "source_file": "lua/client/Tests/RecipeTests.lua", "source_location": "L100"}, {"id": "tests_recipetests_testrecipe", "label": "TestRecipe()", "file_type": "code", "source_file": "lua/client/Tests/RecipeTests.lua", "source_location": "L120"}, {"id": "tests_recipetests_postvalidate", "label": "PostValidate()", "file_type": "code", "source_file": "lua/client/Tests/RecipeTests.lua", "source_location": "L204"}, {"id": "tests_recipetests_shouldskiprecipe", "label": "ShouldSkipRecipe()", "file_type": "code", "source_file": "lua/client/Tests/RecipeTests.lua", "source_location": "L243"}, {"id": "tests_recipetests_ontick", "label": "OnTick()", "file_type": "code", "source_file": "lua/client/Tests/RecipeTests.lua", "source_location": "L252"}, {"id": "tests_recipetests_recipetestone", "label": "RecipeTestOne()", "file_type": "code", "source_file": "lua/client/Tests/RecipeTests.lua", "source_location": "L277"}, {"id": "tests_recipetests_recipetestall", "label": "RecipeTestAll()", "file_type": "code", "source_file": "lua/client/Tests/RecipeTests.lua", "source_location": "L300"}, {"id": "tests_recipetests_recipetestavailableitems", "label": "RecipeTestAvailableItems()", "file_type": "code", "source_file": "lua/client/Tests/RecipeTests.lua", "source_location": "L317"}, {"id": "tests_recipetests_recipetestnumberoftimes", "label": "RecipeTestNumberOfTimes()", "file_type": "code", "source_file": "lua/client/Tests/RecipeTests.lua", "source_location": "L350"}, {"id": "tests_recipetests_recipetestselecteditem", "label": "RecipeTestSelectedItem()", "file_type": "code", "source_file": "lua/client/Tests/RecipeTests.lua", "source_location": "L378"}], "edges": [{"source": "c_users_mw_downloads_coding_pz_lua_client_tests_recipetests_lua", "target": "tests_recipetests_createsourceitem1", "relation": "contains", "confidence": "EXTRACTED", "source_file": "lua/client/Tests/RecipeTests.lua", "source_location": "L1", "weight": 1.0}, {"source": "c_users_mw_downloads_coding_pz_lua_client_tests_recipetests_lua", "target": "tests_recipetests_addtoinv", "relation": "contains", "confidence": "EXTRACTED", "source_file": "lua/client/Tests/RecipeTests.lua", "source_location": "L30", "weight": 1.0}, {"source": "c_users_mw_downloads_coding_pz_lua_client_tests_recipetests_lua", "target": "tests_recipetests_getnumberofitem", "relation": "contains", "confidence": "EXTRACTED", "source_file": "lua/client/Tests/RecipeTests.lua", "source_location": "L43", "weight": 1.0}, {"source": "c_users_mw_downloads_coding_pz_lua_client_tests_recipetests_lua", "target": "tests_recipetests_createsourceitem2", "relation": "contains", "confidence": "EXTRACTED", "source_file": "lua/client/Tests/RecipeTests.lua", "source_location": "L53", "weight": 1.0}, {"source": "c_users_mw_downloads_coding_pz_lua_client_tests_recipetests_lua", "target": "tests_recipetests_createsourceitem", "relation": "contains", "confidence": "EXTRACTED", "source_file": "lua/client/Tests/RecipeTests.lua", "source_location": "L80", "weight": 1.0}, {"source": "c_users_mw_downloads_coding_pz_lua_client_tests_recipetests_lua", "target": "tests_recipetests_setupcontainers", "relation": "contains", "confidence": "EXTRACTED", "source_file": "lua/client/Tests/RecipeTests.lua", "source_location": "L100", "weight": 1.0}, {"source": "c_users_mw_downloads_coding_pz_lua_client_tests_recipetests_lua", "target": "tests_recipetests_testrecipe", "relation": "contains", "confidence": "EXTRACTED", "source_file": "lua/client/Tests/RecipeTests.lua", "source_location": "L120", "weight": 1.0}, {"source": "c_users_mw_downloads_coding_pz_lua_client_tests_recipetests_lua", "target": "tests_recipetests_postvalidate", "relation": "contains", "confidence": "EXTRACTED", "source_file": "lua/client/Tests/RecipeTests.lua", "source_location": "L204", "weight": 1.0}, {"source": "c_users_mw_downloads_coding_pz_lua_client_tests_recipetests_lua", "target": "tests_recipetests_shouldskiprecipe", "relation": "contains", "confidence": "EXTRACTED", "source_file": "lua/client/Tests/RecipeTests.lua", "source_location": "L243", "weight": 1.0}, {"source": "c_users_mw_downloads_coding_pz_lua_client_tests_recipetests_lua", "target": "tests_recipetests_ontick", "relation": "contains", "confidence": "EXTRACTED", "source_file": "lua/client/Tests/RecipeTests.lua", "source_location": "L252", "weight": 1.0}, {"source": "c_users_mw_downloads_coding_pz_lua_client_tests_recipetests_lua", "target": "tests_recipetests_recipetestone", "relation": "contains", "confidence": "EXTRACTED", "source_file": "lua/client/Tests/RecipeTests.lua", "source_location": "L277", "weight": 1.0}, {"source": "c_users_mw_downloads_coding_pz_lua_client_tests_recipetests_lua", "target": "tests_recipetests_recipetestall", "relation": "contains", "confidence": "EXTRACTED", "source_file": "lua/client/Tests/RecipeTests.lua", "source_location": "L300", "weight": 1.0}, {"source": "c_users_mw_downloads_coding_pz_lua_client_tests_recipetests_lua", "target": "tests_recipetests_recipetestavailableitems", "relation": "contains", "confidence": "EXTRACTED", "source_file": "lua/client/Tests/RecipeTests.lua", "source_location": "L317", "weight": 1.0}, {"source": "c_users_mw_downloads_coding_pz_lua_client_tests_recipetests_lua", "target": "tests_recipetests_recipetestnumberoftimes", "relation": "contains", "confidence": "EXTRACTED", "source_file": "lua/client/Tests/RecipeTests.lua", "source_location": "L350", "weight": 1.0}, {"source": "c_users_mw_downloads_coding_pz_lua_client_tests_recipetests_lua", "target": "tests_recipetests_recipetestselecteditem", "relation": "contains", "confidence": "EXTRACTED", "source_file": "lua/client/Tests/RecipeTests.lua", "source_location": "L378", "weight": 1.0}, {"source": "tests_recipetests_createsourceitem2", "target": "tests_recipetests_addtoinv", "relation": "calls", "context": "call", "confidence": "EXTRACTED", "source_file": "lua/client/Tests/RecipeTests.lua", "source_location": "L58", "weight": 1.0}, {"source": "tests_recipetests_createsourceitem2", "target": "tests_recipetests_createsourceitem1", "relation": "calls", "context": "call", "confidence": "EXTRACTED", "source_file": "lua/client/Tests/RecipeTests.lua", "source_location": "L58", "weight": 1.0}, {"source": "tests_recipetests_createsourceitem2", "target": "tests_recipetests_getnumberofitem", "relation": "calls", "context": "call", "confidence": "EXTRACTED", "source_file": "lua/client/Tests/RecipeTests.lua", "source_location": "L64", "weight": 1.0}, {"source": "tests_recipetests_createsourceitem", "target": "tests_recipetests_createsourceitem2", "relation": "calls", "context": "call", "confidence": "EXTRACTED", "source_file": "lua/client/Tests/RecipeTests.lua", "source_location": "L83", "weight": 1.0}, {"source": "tests_recipetests_testrecipe", "target": "tests_recipetests_createsourceitem", "relation": "calls", "context": "call", "confidence": "EXTRACTED", "source_file": "lua/client/Tests/RecipeTests.lua", "source_location": "L145", "weight": 1.0}, {"source": "tests_recipetests_postvalidate", "target": "tests_recipetests_getnumberofitem", "relation": "calls", "context": "call", "confidence": "EXTRACTED", "source_file": "lua/client/Tests/RecipeTests.lua", "source_location": "L208", "weight": 1.0}, {"source": "tests_recipetests_ontick", "target": "tests_recipetests_postvalidate", "relation": "calls", "context": "call", "confidence": "EXTRACTED", "source_file": "lua/client/Tests/RecipeTests.lua", "source_location": "L260", "weight": 1.0}, {"source": "tests_recipetests_ontick", "target": "tests_recipetests_shouldskiprecipe", "relation": "calls", "context": "call", "confidence": "EXTRACTED", "source_file": "lua/client/Tests/RecipeTests.lua", "source_location": "L270", "weight": 1.0}, {"source": "tests_recipetests_ontick", "target": "tests_recipetests_testrecipe", "relation": "calls", "context": "call", "confidence": "EXTRACTED", "source_file": "lua/client/Tests/RecipeTests.lua", "source_location": "L271", "weight": 1.0}, {"source": "tests_recipetests_recipetestone", "target": "tests_recipetests_setupcontainers", "relation": "calls", "context": "call", "confidence": "EXTRACTED", "source_file": "lua/client/Tests/RecipeTests.lua", "source_location": "L279", "weight": 1.0}, {"source": "tests_recipetests_recipetestall", "target": "tests_recipetests_setupcontainers", "relation": "calls", "context": "call", "confidence": "EXTRACTED", "source_file": "lua/client/Tests/RecipeTests.lua", "source_location": "L302", "weight": 1.0}, {"source": "tests_recipetests_recipetestavailableitems", "target": "tests_recipetests_setupcontainers", "relation": "calls", "context": "call", "confidence": "EXTRACTED", "source_file": "lua/client/Tests/RecipeTests.lua", "source_location": "L329", "weight": 1.0}, {"source": "tests_recipetests_recipetestnumberoftimes", "target": "tests_recipetests_setupcontainers", "relation": "calls", "context": "call", "confidence": "EXTRACTED", "source_file": "lua/client/Tests/RecipeTests.lua", "source_location": "L362", "weight": 1.0}, {"source": "tests_recipetests_recipetestselecteditem", "target": "tests_recipetests_setupcontainers", "relation": "calls", "context": "call", "confidence": "EXTRACTED", "source_file": "lua/client/Tests/RecipeTests.lua", "source_location": "L390", "weight": 1.0}], "raw_calls": [{"caller_nid": "tests_recipetests_createsourceitem1", "callee": "InventoryItemFactory.CreateItem", "is_member_call": false, "source_file": "C:\\Users\\MW\\Downloads\\coding\\PZ\\lua\\client\\Tests\\RecipeTests.lua", "source_location": "L4", "receiver": null}, {"caller_nid": "tests_recipetests_createsourceitem1", "callee": "InventoryItemFactory.CreateItem", "is_member_call": false, "source_file": "C:\\Users\\MW\\Downloads\\coding\\PZ\\lua\\client\\Tests\\RecipeTests.lua", "source_location": "L7", "receiver": null}, {"caller_nid": "tests_recipetests_createsourceitem1", "callee": "getScriptManager", "is_member_call": false, "source_file": "C:\\Users\\MW\\Downloads\\coding\\PZ\\lua\\client\\Tests\\RecipeTests.lua", "source_location": "L8", "receiver": null}, {"caller_nid": "tests_recipetests_createsourceitem1", "callee": "InventoryItemFactory.CreateItem", "is_member_call": false, "source_file": "C:\\Users\\MW\\Downloads\\coding\\PZ\\lua\\client\\Tests\\RecipeTests.lua", "source_location": "L9", "receiver": null}, {"caller_nid": "tests_recipetests_createsourceitem1", "callee": "InventoryItemFactory.CreateItem", "is_member_call": false, "source_file": "C:\\Users\\MW\\Downloads\\coding\\PZ\\lua\\client\\Tests\\RecipeTests.lua", "source_location": "L12", "receiver": null}, {"caller_nid": "tests_recipetests_createsourceitem1", "callee": "instanceof", "is_member_call": false, "source_file": "C:\\Users\\MW\\Downloads\\coding\\PZ\\lua\\client\\Tests\\RecipeTests.lua", "source_location": "L13", "receiver": null}, {"caller_nid": "tests_recipetests_createsourceitem1", "callee": "error", "is_member_call": false, "source_file": "C:\\Users\\MW\\Downloads\\coding\\PZ\\lua\\client\\Tests\\RecipeTests.lua", "source_location": "L13", "receiver": null}, {"caller_nid": "tests_recipetests_createsourceitem1", "callee": "InventoryItemFactory.CreateItem", "is_member_call": false, "source_file": "C:\\Users\\MW\\Downloads\\coding\\PZ\\lua\\client\\Tests\\RecipeTests.lua", "source_location": "L16", "receiver": null}, {"caller_nid": "tests_recipetests_addtoinv", "callee": "getPlayer", "is_member_call": false, "source_file": "C:\\Users\\MW\\Downloads\\coding\\PZ\\lua\\client\\Tests\\RecipeTests.lua", "source_location": "L31", "receiver": null}, {"caller_nid": "tests_recipetests_addtoinv", "callee": "ZombRand", "is_member_call": false, "source_file": "C:\\Users\\MW\\Downloads\\coding\\PZ\\lua\\client\\Tests\\RecipeTests.lua", "source_location": "L34", "receiver": null}, {"caller_nid": "tests_recipetests_createsourceitem2", "callee": "getPlayer", "is_member_call": false, "source_file": "C:\\Users\\MW\\Downloads\\coding\\PZ\\lua\\client\\Tests\\RecipeTests.lua", "source_location": "L54", "receiver": null}, {"caller_nid": "tests_recipetests_createsourceitem2", "callee": "table.insert", "is_member_call": false, "source_file": "C:\\Users\\MW\\Downloads\\coding\\PZ\\lua\\client\\Tests\\RecipeTests.lua", "source_location": "L59", "receiver": null}, {"caller_nid": "tests_recipetests_createsourceitem2", "callee": "table.insert", "is_member_call": false, "source_file": "C:\\Users\\MW\\Downloads\\coding\\PZ\\lua\\client\\Tests\\RecipeTests.lua", "source_location": "L64", "receiver": null}, {"caller_nid": "tests_recipetests_createsourceitem2", "callee": "getScriptManager", "is_member_call": false, "source_file": "C:\\Users\\MW\\Downloads\\coding\\PZ\\lua\\client\\Tests\\RecipeTests.lua", "source_location": "L66", "receiver": null}, {"caller_nid": "tests_recipetests_createsourceitem2", "callee": "table.insert", "is_member_call": false, "source_file": "C:\\Users\\MW\\Downloads\\coding\\PZ\\lua\\client\\Tests\\RecipeTests.lua", "source_location": "L68", "receiver": null}, {"caller_nid": "tests_recipetests_createsourceitem2", "callee": "table.insert", "is_member_call": false, "source_file": "C:\\Users\\MW\\Downloads\\coding\\PZ\\lua\\client\\Tests\\RecipeTests.lua", "source_location": "L71", "receiver": null}, {"caller_nid": "tests_recipetests_createsourceitem2", "callee": "math.floor", "is_member_call": false, "source_file": "C:\\Users\\MW\\Downloads\\coding\\PZ\\lua\\client\\Tests\\RecipeTests.lua", "source_location": "L71", "receiver": null}, {"caller_nid": "tests_recipetests_createsourceitem2", "callee": "table.insert", "is_member_call": false, "source_file": "C:\\Users\\MW\\Downloads\\coding\\PZ\\lua\\client\\Tests\\RecipeTests.lua", "source_location": "L75", "receiver": null}, {"caller_nid": "tests_recipetests_createsourceitem", "callee": "getPlayer", "is_member_call": false, "source_file": "C:\\Users\\MW\\Downloads\\coding\\PZ\\lua\\client\\Tests\\RecipeTests.lua", "source_location": "L81", "receiver": null}, {"caller_nid": "tests_recipetests_createsourceitem", "callee": "getScriptManager", "is_member_call": false, "source_file": "C:\\Users\\MW\\Downloads\\coding\\PZ\\lua\\client\\Tests\\RecipeTests.lua", "source_location": "L88", "receiver": null}, {"caller_nid": "tests_recipetests_setupcontainers", "callee": "getPlayer", "is_member_call": false, "source_file": "C:\\Users\\MW\\Downloads\\coding\\PZ\\lua\\client\\Tests\\RecipeTests.lua", "source_location": "L101", "receiver": null}, {"caller_nid": "tests_recipetests_setupcontainers", "callee": "InventoryItemFactory.CreateItem", "is_member_call": false, "source_file": "C:\\Users\\MW\\Downloads\\coding\\PZ\\lua\\client\\Tests\\RecipeTests.lua", "source_location": "L109", "receiver": null}, {"caller_nid": "tests_recipetests_setupcontainers", "callee": "getPlayerInventory", "is_member_call": false, "source_file": "C:\\Users\\MW\\Downloads\\coding\\PZ\\lua\\client\\Tests\\RecipeTests.lua", "source_location": "L112", "receiver": null}, {"caller_nid": "tests_recipetests_setupcontainers", "callee": "getPlayerLoot", "is_member_call": false, "source_file": "C:\\Users\\MW\\Downloads\\coding\\PZ\\lua\\client\\Tests\\RecipeTests.lua", "source_location": "L113", "receiver": null}, {"caller_nid": "tests_recipetests_setupcontainers", "callee": "ISInventoryPaneContextMenu.getContainers", "is_member_call": false, "source_file": "C:\\Users\\MW\\Downloads\\coding\\PZ\\lua\\client\\Tests\\RecipeTests.lua", "source_location": "L114", "receiver": null}, {"caller_nid": "tests_recipetests_testrecipe", "callee": "getPlayer", "is_member_call": false, "source_file": "C:\\Users\\MW\\Downloads\\coding\\PZ\\lua\\client\\Tests\\RecipeTests.lua", "source_location": "L121", "receiver": null}, {"caller_nid": "tests_recipetests_testrecipe", "callee": "getCell", "is_member_call": false, "source_file": "C:\\Users\\MW\\Downloads\\coding\\PZ\\lua\\client\\Tests\\RecipeTests.lua", "source_location": "L128", "receiver": null}, {"caller_nid": "tests_recipetests_testrecipe", "callee": "getPlayerInventory", "is_member_call": false, "source_file": "C:\\Users\\MW\\Downloads\\coding\\PZ\\lua\\client\\Tests\\RecipeTests.lua", "source_location": "L134", "receiver": null}, {"caller_nid": "tests_recipetests_testrecipe", "callee": "getPlayerLoot", "is_member_call": false, "source_file": "C:\\Users\\MW\\Downloads\\coding\\PZ\\lua\\client\\Tests\\RecipeTests.lua", "source_location": "L135", "receiver": null}, {"caller_nid": "tests_recipetests_testrecipe", "callee": "ISInventoryPaneContextMenu.getContainers", "is_member_call": false, "source_file": "C:\\Users\\MW\\Downloads\\coding\\PZ\\lua\\client\\Tests\\RecipeTests.lua", "source_location": "L136", "receiver": null}, {"caller_nid": "tests_recipetests_testrecipe", "callee": "RecipeManager.getNumberOfTimesRecipeCanBeDone", "is_member_call": false, "source_file": "C:\\Users\\MW\\Downloads\\coding\\PZ\\lua\\client\\Tests\\RecipeTests.lua", "source_location": "L154", "receiver": null}, {"caller_nid": "tests_recipetests_testrecipe", "callee": "tostring", "is_member_call": false, "source_file": "C:\\Users\\MW\\Downloads\\coding\\PZ\\lua\\client\\Tests\\RecipeTests.lua", "source_location": "L156", "receiver": null}, {"caller_nid": "tests_recipetests_testrecipe", "callee": "RecipeManager.IsRecipeValid", "is_member_call": false, "source_file": "C:\\Users\\MW\\Downloads\\coding\\PZ\\lua\\client\\Tests\\RecipeTests.lua", "source_location": "L165", "receiver": null}, {"caller_nid": "tests_recipetests_testrecipe", "callee": "tostring", "is_member_call": false, "source_file": "C:\\Users\\MW\\Downloads\\coding\\PZ\\lua\\client\\Tests\\RecipeTests.lua", "source_location": "L167", "receiver": null}, {"caller_nid": "tests_recipetests_testrecipe", "callee": "RecipeManager.IsRecipeValid", "is_member_call": false, "source_file": "C:\\Users\\MW\\Downloads\\coding\\PZ\\lua\\client\\Tests\\RecipeTests.lua", "source_location": "L175", "receiver": null}, {"caller_nid": "tests_recipetests_testrecipe", "callee": "tostring", "is_member_call": false, "source_file": "C:\\Users\\MW\\Downloads\\coding\\PZ\\lua\\client\\Tests\\RecipeTests.lua", "source_location": "L176", "receiver": null}, {"caller_nid": "tests_recipetests_testrecipe", "callee": "ZombRand", "is_member_call": false, "source_file": "C:\\Users\\MW\\Downloads\\coding\\PZ\\lua\\client\\Tests\\RecipeTests.lua", "source_location": "L184", "receiver": null}, {"caller_nid": "tests_recipetests_testrecipe", "callee": "ZombRand", "is_member_call": false, "source_file": "C:\\Users\\MW\\Downloads\\coding\\PZ\\lua\\client\\Tests\\RecipeTests.lua", "source_location": "L187", "receiver": null}, {"caller_nid": "tests_recipetests_testrecipe", "callee": "ISInventoryPaneContextMenu.OnCraft", "is_member_call": false, "source_file": "C:\\Users\\MW\\Downloads\\coding\\PZ\\lua\\client\\Tests\\RecipeTests.lua", "source_location": "L191", "receiver": null}, {"caller_nid": "tests_recipetests_testrecipe", "callee": "getPerformance", "is_member_call": false, "source_file": "C:\\Users\\MW\\Downloads\\coding\\PZ\\lua\\client\\Tests\\RecipeTests.lua", "source_location": "L193", "receiver": null}, {"caller_nid": "tests_recipetests_testrecipe", "callee": "RecipeManager.PerformMakeItem", "is_member_call": false, "source_file": "C:\\Users\\MW\\Downloads\\coding\\PZ\\lua\\client\\Tests\\RecipeTests.lua", "source_location": "L200", "receiver": null}, {"caller_nid": "tests_recipetests_postvalidate", "callee": "getScriptManager", "is_member_call": false, "source_file": "C:\\Users\\MW\\Downloads\\coding\\PZ\\lua\\client\\Tests\\RecipeTests.lua", "source_location": "L206", "receiver": null}, {"caller_nid": "tests_recipetests_postvalidate", "callee": "tostring", "is_member_call": false, "source_file": "C:\\Users\\MW\\Downloads\\coding\\PZ\\lua\\client\\Tests\\RecipeTests.lua", "source_location": "L211", "receiver": null}, {"caller_nid": "tests_recipetests_postvalidate", "callee": "tostring", "is_member_call": false, "source_file": "C:\\Users\\MW\\Downloads\\coding\\PZ\\lua\\client\\Tests\\RecipeTests.lua", "source_location": "L211", "receiver": null}, {"caller_nid": "tests_recipetests_ontick", "callee": "isKeyDown", "is_member_call": false, "source_file": "C:\\Users\\MW\\Downloads\\coding\\PZ\\lua\\client\\Tests\\RecipeTests.lua", "source_location": "L253", "receiver": null}, {"caller_nid": "tests_recipetests_ontick", "callee": "table.wipe", "is_member_call": false, "source_file": "C:\\Users\\MW\\Downloads\\coding\\PZ\\lua\\client\\Tests\\RecipeTests.lua", "source_location": "L254", "receiver": null}, {"caller_nid": "tests_recipetests_ontick", "callee": "getPlayer", "is_member_call": false, "source_file": "C:\\Users\\MW\\Downloads\\coding\\PZ\\lua\\client\\Tests\\RecipeTests.lua", "source_location": "L256", "receiver": null}, {"caller_nid": "tests_recipetests_ontick", "callee": "ISTimedActionQueue.getTimedActionQueue", "is_member_call": false, "source_file": "C:\\Users\\MW\\Downloads\\coding\\PZ\\lua\\client\\Tests\\RecipeTests.lua", "source_location": "L257", "receiver": null}, {"caller_nid": "tests_recipetests_ontick", "callee": "table.remove", "is_member_call": false, "source_file": "C:\\Users\\MW\\Downloads\\coding\\PZ\\lua\\client\\Tests\\RecipeTests.lua", "source_location": "L269", "receiver": null}, {"caller_nid": "tests_recipetests_recipetestone", "callee": "getPlayer", "is_member_call": false, "source_file": "C:\\Users\\MW\\Downloads\\coding\\PZ\\lua\\client\\Tests\\RecipeTests.lua", "source_location": "L278", "receiver": null}, {"caller_nid": "tests_recipetests_recipetestone", "callee": "getAllRecipes", "is_member_call": false, "source_file": "C:\\Users\\MW\\Downloads\\coding\\PZ\\lua\\client\\Tests\\RecipeTests.lua", "source_location": "L280", "receiver": null}, {"caller_nid": "tests_recipetests_recipetestone", "callee": "table.insert", "is_member_call": false, "source_file": "C:\\Users\\MW\\Downloads\\coding\\PZ\\lua\\client\\Tests\\RecipeTests.lua", "source_location": "L286", "receiver": null}, {"caller_nid": "tests_recipetests_recipetestone", "callee": "Events.OnTick.Add", "is_member_call": false, "source_file": "C:\\Users\\MW\\Downloads\\coding\\PZ\\lua\\client\\Tests\\RecipeTests.lua", "source_location": "L294", "receiver": null}, {"caller_nid": "tests_recipetests_recipetestall", "callee": "getPlayer", "is_member_call": false, "source_file": "C:\\Users\\MW\\Downloads\\coding\\PZ\\lua\\client\\Tests\\RecipeTests.lua", "source_location": "L301", "receiver": null}, {"caller_nid": "tests_recipetests_recipetestall", "callee": "getAllRecipes", "is_member_call": false, "source_file": "C:\\Users\\MW\\Downloads\\coding\\PZ\\lua\\client\\Tests\\RecipeTests.lua", "source_location": "L303", "receiver": null}, {"caller_nid": "tests_recipetests_recipetestall", "callee": "table.insert", "is_member_call": false, "source_file": "C:\\Users\\MW\\Downloads\\coding\\PZ\\lua\\client\\Tests\\RecipeTests.lua", "source_location": "L307", "receiver": null}, {"caller_nid": "tests_recipetests_recipetestall", "callee": "Events.OnTick.Add", "is_member_call": false, "source_file": "C:\\Users\\MW\\Downloads\\coding\\PZ\\lua\\client\\Tests\\RecipeTests.lua", "source_location": "L311", "receiver": null}, {"caller_nid": "tests_recipetests_recipetestavailableitems", "callee": "getPlayer", "is_member_call": false, "source_file": "C:\\Users\\MW\\Downloads\\coding\\PZ\\lua\\client\\Tests\\RecipeTests.lua", "source_location": "L318", "receiver": null}, {"caller_nid": "tests_recipetests_recipetestavailableitems", "callee": "getCell", "is_member_call": false, "source_file": "C:\\Users\\MW\\Downloads\\coding\\PZ\\lua\\client\\Tests\\RecipeTests.lua", "source_location": "L324", "receiver": null}, {"caller_nid": "tests_recipetests_recipetestavailableitems", "callee": "RecipeManager.getAvailableItemsAll", "is_member_call": false, "source_file": "C:\\Users\\MW\\Downloads\\coding\\PZ\\lua\\client\\Tests\\RecipeTests.lua", "source_location": "L335", "receiver": null}, {"caller_nid": "tests_recipetests_recipetestavailableitems", "callee": "RecipeManager.getAvailableItemsNeeded", "is_member_call": false, "source_file": "C:\\Users\\MW\\Downloads\\coding\\PZ\\lua\\client\\Tests\\RecipeTests.lua", "source_location": "L341", "receiver": null}, {"caller_nid": "tests_recipetests_recipetestnumberoftimes", "callee": "getPlayer", "is_member_call": false, "source_file": "C:\\Users\\MW\\Downloads\\coding\\PZ\\lua\\client\\Tests\\RecipeTests.lua", "source_location": "L351", "receiver": null}, {"caller_nid": "tests_recipetests_recipetestnumberoftimes", "callee": "getCell", "is_member_call": false, "source_file": "C:\\Users\\MW\\Downloads\\coding\\PZ\\lua\\client\\Tests\\RecipeTests.lua", "source_location": "L357", "receiver": null}, {"caller_nid": "tests_recipetests_recipetestnumberoftimes", "callee": "RecipeManager.getNumberOfTimesRecipeCanBeDone", "is_member_call": false, "source_file": "C:\\Users\\MW\\Downloads\\coding\\PZ\\lua\\client\\Tests\\RecipeTests.lua", "source_location": "L369", "receiver": null}, {"caller_nid": "tests_recipetests_recipetestselecteditem", "callee": "getPlayer", "is_member_call": false, "source_file": "C:\\Users\\MW\\Downloads\\coding\\PZ\\lua\\client\\Tests\\RecipeTests.lua", "source_location": "L379", "receiver": null}, {"caller_nid": "tests_recipetests_recipetestselecteditem", "callee": "getCell", "is_member_call": false, "source_file": "C:\\Users\\MW\\Downloads\\coding\\PZ\\lua\\client\\Tests\\RecipeTests.lua", "source_location": "L385", "receiver": null}, {"caller_nid": "tests_recipetests_recipetestselecteditem", "callee": "RecipeManager.PerformMakeItem", "is_member_call": false, "source_file": "C:\\Users\\MW\\Downloads\\coding\\PZ\\lua\\client\\Tests\\RecipeTests.lua", "source_location": "L399", "receiver": null}]}