{
  "wave_name": "wave3",
  "wave_class": "COLLISION_HEAVY",
  "bucket_ids": [
    "Consumable.3-E",
    "Furniture.7-A",
    "Vehicle.8-A",
    "Wearable.6-G"
  ],
  "canonical_seed_bucket_ids": [],
  "exploratory_reference_bucket_ids": [],
  "pending_canonical_execution_bucket_ids": [],
  "bucket_row_counts": {
    "Consumable.3-E": 3,
    "Furniture.7-A": 140,
    "Vehicle.8-A": 46,
    "Wearable.6-G": 130
  },
  "total_bucket_count": 4,
  "total_row_count": 319,
  "pending_canonical_execution_row_count": 0
}
