{
  "pilot_name": "wave4_wearable6e",
  "bucket_id": "Wearable.6-E",
  "source_review_file": "Wearable.6-E.acquisition.jsonl",
  "row_count": 19,
  "coverage_disposition_breakdown": {
    "ACQ_HINT": 19
  },
  "contamination": {
    "system_excluded": 0,
    "unreviewed": 0
  },
  "fulltypes": [
    "Base.Shoes_ArmyBoots",
    "Base.Shoes_ArmyBootsDesert",
    "Base.Shoes_Black",
    "Base.Shoes_BlackBoots",
    "Base.Shoes_BlueTrainers",
    "Base.Shoes_Bowling",
    "Base.Shoes_Brown",
    "Base.Shoes_Fancy",
    "Base.Shoes_FlipFlop",
    "Base.Shoes_Random",
    "Base.Shoes_RedTrainers",
    "Base.Shoes_RidingBoots",
    "Base.Shoes_Sandals",
    "Base.Shoes_Slippers",
    "Base.Shoes_Strapped",
    "Base.Shoes_TrainerTINT",
    "Base.Shoes_Wellies",
    "Base.Socks_Ankle",
    "Base.Socks_Long"
  ],
  "phase2_snapshot_sha256": "619d7aaddea1991c6e81557a880f4593d3ffeb1883a77d630261b3df1e47d01e"
}